<!-- TB3D 1.1.0.0.0.4 -->
<!-- Translated and corrected by Steve90k for fluency and ease of reading. Edited and proofed by Sword2012 for clarity, brevity, and consistency. 21 Jan 16 -->
<string id="bar_darklab_documents_1_hint">
	<text>Borov</text>
</string>
<string id="bar_darklab_documents_2_hint">
	<text>Tunnel</text>
</string>
<string id="bar_darklab_documents_3_hint">
	<text>Laboreingang</text>
</string>
<string id="bar_darklab_documents_4_hint">
	<text>Rohr</text>
</string>
<string id="bar_darklab_documents2_1_hint">
	<text>Dokumente aus dem Labor</text>
</string>
<string id="bar_darklab_documents2_2_hint">
	<text>Wirt</text>
</string>
<string id="val_captive_help_1_hint">
	<text>Bullet</text>
</string>
<string id="val_captive_help_2_hint">
	<text>Gefangener</text>
</string>
<string id="val_come_to_trader_1_hint">
	<text>Südtor</text>
</string>
<string id="val_come_to_trader_2_hint">
	<text>Händler</text>
</string>
<string id="val_prisoner_help_main_hint">
	<text>Gefangener Wächter</text>
</string>
<string id="val_sos_help_main_hint">
	<text>Verwundeter Stalker</text>
</string>
<string id="val_zone_bandits_hint">
	<text>Banditenlager</text>
</string>
<string id="val_zone_farm_hint">
	<text>Bauernhof.\nGerücht über ein Gauss Rifle!</text>
</string>
<string id="val_zone_monolith_hint">
	<text>Alte Fabrik</text>
</string>
<string id="val_zone_pipe_hint">
	<text>Kanalrohr</text>
</string>
<string id="val_zone_robbers_hint">
	<text>Verlassene Schweinezucht</text>
</string>
<string id="val_zone_south_gate_hint">
	<text>Tore</text>
</string>
<!--Created/Modified with S.T.A.L.K.E.R. Dialog Extended Editor by Marty Sheppard/ Version: 0.96i ( 2017/02/17) =!!= Last changed: 24.04.2017 03:50:42 -->
